Metadata-Version: 2.1
Name: jsfiddle-build
Version: 2019.4.12
Summary: build html file from jsfiddle files
Home-page: https://github.com/looking-for-a-job/jsfiddle-build.py
License: UNKNOWN
Keywords: jsfiddle
Platform: UNKNOWN
Classifier: Operating System :: OS Independent
Classifier: Programming Language :: Python
Classifier: Programming Language :: Python :: 2
Classifier: Programming Language :: Python :: 2.7
Classifier: Programming Language :: Python :: 3
Classifier: Programming Language :: Python :: 3.4
Classifier: Programming Language :: Python :: 3.5
Classifier: Programming Language :: Python :: 3.6
Classifier: Programming Language :: Python :: 3.7
Requires-Dist: PyYAML
Requires-Dist: click
Requires-Dist: public
Requires-Dist: setuptools
